pydrag/__init__.py
pydrag/constants.py
pydrag/exceptions.py
pydrag/py.typed
pydrag/services.py
pydrag/utils.py
pydrag/version.py
pydrag/models/__init__.py
pydrag/models/album.py
pydrag/models/artist.py
pydrag/models/auth.py
pydrag/models/common.py
pydrag/models/tag.py
pydrag/models/track.py
pydrag/models/user.py
pydrag-22.5.dist-info/LICENSE
pydrag-22.5.dist-info/METADATA
pydrag-22.5.dist-info/WHEEL
pydrag-22.5.dist-info/top_level.txt
pydrag-22.5.dist-info/RECORD
